{
  "id": "a-star-search",
  "title": "A* 搜索",
  "clusterId": "search-solving",
  "shortSummary": "A* 用“已经走了多少”和“预计还差多少”共同排序，是路径规划中兼顾效率与最优性的经典算法。",
  "coreIdea": "**A* 的聪明之处在于不盲目扩展**：它同时看实际代价 \\(g(n)\\) 和启发式估计 \\(h(n)\\)，优先探索总估计代价最低的节点。",
  "principles": [
    "**开放表**：保存已经发现但尚未扩展的候选节点，每次取 \\(f(n)\\) 最小者。",
    "**关闭表**：记录已经扩展过的节点，避免重复搜索和循环。",
    "**启发式质量**：若 \\(h(n)\\) 从不高估真实剩余代价，A* 可以保证找到最优路径。"
  ],
  "formula": "$$f(n)=g(n)+h(n)$$",
  "keyTerms": [
    "开放表",
    "关闭表",
    "路径代价",
    "启发式函数",
    "可采纳性",
    "一致性"
  ],
  "comparisons": [
    "当 \\(h(n)=0\\) 时，A* 退化为 Dijkstra，更稳但探索范围更大。",
    "当过度依赖 \\(h(n)\\) 时，搜索会更像贪心最佳优先搜索，速度快但可能失去最优性。"
  ],
  "applications": [
    "机器人在栅格地图中导航",
    "游戏角色寻路与动态避障",
    "物流、仓储和任务规划中的候选路径生成"
  ],
  "visualType": "search",
  "animationType": "search",
  "visualSuggestion": "用网格显示起点、目标、障碍、已扩展节点和最终路径，突出启发式如何缩小搜索范围。",
  "animationSuggestion": "逐格点亮搜索前沿，先显示候选扩张，再收束成最短路径。",
  "ideologicalElement": "A* 展示了“经验估计”和“严格约束”结合的价值：既要快，也要知道什么时候可以相信结果。",
  "difficulty": "中等",
  "prerequisites": [
    "状态空间搜索",
    "图搜索",
    "最短路径"
  ],
  "intuition": "录屏时可以把 \\(g(n)\\) 讲成“已经花掉的路费”，把 \\(h(n)\\) 讲成“导航预计还要花的路费”。A* 每次选择总账最便宜的路线继续试。",
  "misconceptions": [
    "启发式不是越大胆越好；高估真实代价可能破坏最优性。",
    "A* 不只适用于二维地图，只要问题能表示成状态图，就可以设计启发式进行搜索。"
  ],
  "history": "A* 是人工智能早期搜索研究中的代表算法，至今仍广泛用于路径规划、游戏 AI 和机器人系统。",
  "prosCons": {
    "pros": [
      "在合适启发式下兼顾效率和最优性",
      "过程可解释，便于可视化",
      "适用于路径规划和一般图搜索"
    ],
    "cons": [
      "启发式设计影响很大",
      "大图上开放表可能占用大量内存",
      "动态环境中需要重规划或增量算法配合"
    ]
  },
  "qa": [
    {
      "q": "A* 为什么常比 Dijkstra 搜得少？",
      "a": "因为启发式会把搜索方向拉向目标区域，减少与目标无关的扩展。"
    }
  ],
  "importance": 0.6,
  "pos": [
    1696.8,
    1422.8
  ],
  "scale": 1.44
}
