{
  "id": "distribution-shift",
  "title": "分布偏移",
  "clusterId": "ethics-safety",
  "shortSummary": "就像考试题和平时练习题不一样，导致考不好。",
  "coreIdea": "分布偏移的核心在于训练分布 $P_{\\text{train}$}(X,Y) 与测试分布 $P_{\\text{test}$}(X,Y) 不一致。常见类型：\n1. 协变量偏移：P(X) 变化但 P(Y|X) 不变，例如训练数据中猫的图片多为室内，测试时多为室外。\n2. 标签偏移：P(Y) 变化但 P(X|Y) 不变，例如训练时正负样本比例1:1，测试时1:9。\n3. 概念漂移：P(Y|X) 随时间变化，例如用户兴趣随时间改变。\n\n检测方法：比较训练和测试特征的分布（如MMD、KS检验）。\n缓解方法：\n- 协变量偏移：重要性加权，w(x)=$P_{\\text{test}$}(x)/$P_{\\text{train}$}(x)。\n- 标签偏移：利用混淆矩阵估计。\n- 概念漂移：在线学习、模型重训练。\n\n例子：训练一个猫狗分类器，训练集全是家猫家狗，测试集包含野生猫狗（背景、姿态不同），导致准确率下降。",
  "principles": [
    "分布偏移的核心在于训练分布 $P_{\\text{train}$}(X,Y) 与测试分布 $P_{\\text{test}$}(X,Y) 不一致",
    "常见类型：",
    "1. 协变量偏移：P(X) 变化但 P(Y|X) 不变，例如训练数据中猫的图片多为室内，测试时多为室外",
    "2. 标签偏移：P(Y) 变化但 P(X|Y) 不变，例如训练时正负样本比例1:1，测试时1:9",
    "讲解 分布偏移 时，先用一个可手算或可画图的小例子建立直觉，再回到公式、流程或模型结构。"
  ],
  "keyTerms": [
    "分布偏移",
    "Distribution Shift",
    "核心概念",
    "输入输出",
    "适用条件",
    "局限性",
    "鲁棒性",
    "泛化"
  ],
  "applications": [
    "自动驾驶中不同天气、城市的数据分布差异",
    "医疗诊断中不同医院、设备的影像分布偏移",
    "推荐系统中用户兴趣随时间的概念漂移"
  ],
  "difficulty": "中等",
  "importance": 0.104,
  "comparisons": [
    "dim_shift_type: 协变量偏移、标签偏移、概念漂移",
    "dim_correction_method: 重要性加权、混淆矩阵估计、在线学习"
  ],
  "formula": "协变量偏移：$P_{\\text{test}$}(Y|X)=$P_{\\text{train}$}(Y|X) 但 $P_{\\text{test}$}(X) eq $P_{\\text{train}$}(X)。\n重要性加权：$\\mathbb{E}_{P_{\\text{test}}}[\\ell(f(X),Y)]=\\mathbb{E}_{P_{\\text{train}}}\\left[\\frac{P_{\\text{test}}(X)}{P_{\\text{train}}(X)}\\ell(f(X),Y)\\right]$。",
  "aliases": [
    "数据集偏移",
    "协变量偏移",
    "概念漂移"
  ],
  "intuition": "就像考试题和平时练习题不一样，导致考不好。",
  "misconceptions": [
    "分布偏移 不是只需要记住名称；学习时要同时看清它的输入、输出、核心假设和失效条件。"
  ],
  "history": "分布偏移的概念最早可追溯到20世纪80年代统计学习领域，但系统研究始于2000年左右。2007年，Quionero-Candela等人出版了《Dataset Shift in Machine Learning》一书，奠定了理论基础。2010年后，随着深度学习兴起，分布偏移在迁移学习、领域适应、鲁棒性等方向得到广泛关注。2019年，概念漂移在在线学习和流数据挖掘中成为热点。",
  "yearIntroduced": 2007,
  "prosCons": {
    "pros": [
      "重要性加权理论完备，可有效纠正协变量偏移",
      "分布偏移检测方法多样，易于实现"
    ],
    "cons": [
      "重要性权重估计在高维空间不稳定，方差大",
      "概念漂移难以实时检测和适应，需要持续监控"
    ]
  },
  "qa": [
    {
      "q": "请解释协变量偏移和标签偏移的区别，并举例说明。",
      "a": "协变量偏移是输入分布P(X)改变，但条件分布P(Y|X)不变；标签偏移是输出分布P(Y)改变，但P(X|Y)不变。例如：训练集猫狗各半，测试集猫占90%狗占10%是标签偏移；训练集猫狗图片背景单一，测试集背景复杂是协变量偏移。"
    },
    {
      "q": "如何检测分布偏移？请列出至少两种方法。",
      "a": "1. 最大均值差异（MMD）：计算训练和测试特征在RKHS中的距离。2. 核密度估计：分别估计训练和测试的密度，计算KL散度或JS散度。3. 分类器检测：训练一个分类器区分训练和测试样本，若分类准确率显著高于随机，则存在偏移。"
    },
    {
      "q": "重要性加权如何用于协变量偏移校正？有什么局限性？",
      "a": "重要性加权通过给每个训练样本赋予权重w(x)=P_test(x)/P_train(x)来调整损失函数，使得加权后的训练分布接近测试分布。局限性：权重估计在高维空间困难，易出现极端权重导致方差大；当P_train(x)接近0时权重趋于无穷，不稳定。"
    }
  ],
  "prerequisites": [
    "neural-network"
  ],
  "pos": [
    1589,
    2395.3
  ],
  "scale": 0.75
}