{
  "id": "semantic-segmentation",
  "title": "语义分割",
  "clusterId": "cv",
  "shortSummary": "语义分割为图像中的每个像素预测类别。",
  "coreIdea": "从图像级理解进一步细化到像素级理解，形成密集预测结果。",
  "principles": [
    "编码器提取上下文特征",
    "解码器恢复空间分辨率",
    "每个像素输出类别概率"
  ],
  "keyTerms": [
    "像素级分类",
    "掩膜",
    "编码器-解码器",
    "mIoU"
  ],
  "comparisons": [
    "目标检测给框，语义分割给像素级区域。"
  ],
  "applications": [
    "医学器官分割",
    "遥感地物分类",
    "自动驾驶道路理解"
  ],
  "visualType": "vision",
  "difficulty": "进阶",
  "prerequisites": [],
  "importance": 0.6,
  "pos": [
    2318.7,
    429
  ],
  "scale": 1.44
}